{
"questions":[ 
     {"category":"Harry Potter", "question":"Harry Potter"},
     {"category":"Harry Potter", "question":"Ron Weasley"},
     {"category":"Harry Potter", "question":"Lord Voldemort"},
     {"category":"Harry Potter", "question":"Phineas Nigellus Black"},
     {"category":"Harry Potter", "question":"Sirius Black"},
     {"category":"Harry Potter", "question":"Severus Snape"},
     {"category":"Harry Potter", "question":"Cho Chang"},
     {"category":"Harry Potter", "question":"Draco Malfoy"},
     {"category":"Harry Potter", "question":"Fleur Delacour"},
     {"category":"Harry Potter", "question":"Cedric Diggory"},
     {"category":"Harry Potter", "question":"Albus Dumbledore"},
     {"category":"Harry Potter", "question":"Dudley Dursley"},
     {"category":"Harry Potter", "question":"Petunia Dursley"},
     {"category":"Harry Potter", "question":"Vernon Dursley"},
     {"category":"Harry Potter", "question":"Argus Filch"},
     {"category":"Harry Potter", "question":"Hermione Granger"},
     {"category":"Harry Potter", "question":"Godric Gryffindor"},
     {"category":"Harry Potter", "question":"Rubeus Hagrid"},
     {"category":"Harry Potter", "question":"Madam Hooch"},
     {"category":"Harry Potter", "question":"Helga Hufflepuff"},
     {"category":"Harry Potter", "question":"Viktor Krum"},
     {"category":"Harry Potter", "question":"Bellatrix Lestrange"},
     {"category":"Harry Potter", "question":"Neville Longbottom"},
     {"category":"Animated Movies", "question":"Finding Nemo"},
     {"category":"Animated Movies", "question":"Toy Story"},
     {"category":"Best Movie Oscar Winners", "question":"Moonlight"},
     {"category":"Best Movie Oscar Winners", "question":"Spotlight"},
     {"category":"Best Movie Oscar Winners", "question":"Birdman"},
     {"category":"Best Movie Oscar Winners", "question":"Argo"},
     {"category":"Best Movie Oscar Winners", "question":"The Artist"},
     {"category":"Movie Characters", "question":"Batman"},
     {"category":"Movie Characters", "question":"Superman"},
     {"category":"Movie Characters", "question":"Terminator"},
     {"category":"Movie Characters", "question":"Spiderman"},
     {"category":"Movie Characters", "question":"Jack Sparrow"},
     {"category":"Movie Characters", "question":"Sheldon Cooper"},
     {"category":"Movie Characters", "question":"Hannibal Lecter"},
     {"category":"Movie Characters", "question":"Captain America"},
     {"category":"Movie Characters", "question":"Edward Scissorhand"},
     {"category":"Movie Characters", "question":"Robin Hood"},
     {"category":"Movie Characters", "question":"Green Lantern"},
     {"category":"Movie Characters", "question":"Winnetou"},
     {"category":"Movie Characters", "question":"Sherlock Holmes"},
     {"category":"Movie Characters", "question":"James Kirk"},
     {"category":"Movie Characters", "question":"Spock"},
     {"category":"Movie Characters", "question":"Jean Luc Picard"},
     {"category":"Movie Characters", "question":"Luke Skywalker"}
]}